LICENSE
MANIFEST.in
README.md
pyproject.toml
setup.py
PyNVTX/PyNVTX_backend.cpp
PyNVTX/PyNVTX_backend.cu
PyNVTX/__init__.py
PyNVTX/__main__.py
PyNVTX/registry.py
PyNVTX/singleton.py
PyNVTX.egg-info/PKG-INFO
PyNVTX.egg-info/SOURCES.txt
PyNVTX.egg-info/dependency_links.txt
PyNVTX.egg-info/requires.txt
PyNVTX.egg-info/top_level.txt
test/test-deviceinfo.py
test/test-nvtx.py