Metadata-Version: 2.1
Name: PyNVTX
Version: 0.3.1
Summary: A thin python wrapper for the nvToolsExt (NVTX) library, using pybind11 ... with some bells and whistles thrown in for good measure.
Home-page: https://github.com/JBlaschke/PyNVTX
Author: Johannes Blaschke
Author-email: johannes@blaschke.science
License: UNKNOWN
Platform: UNKNOWN
Classifier: Programming Language :: Python :: 3
Classifier: License :: OSI Approved :: MIT License
Classifier: Operating System :: OS Independent
Requires-Python: >=3.6
